es_gui.py
es_viewer-1.2.11.dist-info/LICENSE
es_viewer-1.2.11.dist-info/METADATA
es_viewer-1.2.11.dist-info/WHEEL
es_viewer-1.2.11.dist-info/entry_points.txt
es_viewer-1.2.11.dist-info/top_level.txt
es_viewer-1.2.11.dist-info/RECORD
