Metadata-Version: 2.1
Name: es-viewer
Version: 1.2.11
Summary: A lightweight, cross-platform desktop GUI for Elasticsearch
Home-page: https://github.com/isee15/es-viewer
Author: 乖猫记账
Author-email: meizhitu@gmail.com
License: UNKNOWN
Platform: UNKNOWN
Classifier: Programming Language :: Python :: 3
Classifier: License :: OSI Approved :: MIT License
Classifier: Operating System :: OS Independent
Classifier: Topic :: Database :: Front-Ends
Classifier: Environment :: X11 Applications :: Qt
Requires-Python: >=3.6
License-File: LICENSE
Requires-Dist: PyQt6
Requires-Dist: requests
Requires-Dist: urllib3
